package com.flurry.sdk;

public class ce extends fi
{
  static int a;
  private static final String g = ce.class.getSimpleName();
  String b;
  String c;
  String d;
  byte[] e;
  ch f;

  static
  {
    a = 15000;
  }

  public ce(String paramString1, String paramString2, String paramString3, byte[] paramArrayOfByte, ch paramch)
  {
    this.b = paramString1;
    this.c = paramString2;
    this.d = paramString3;
    this.e = paramArrayOfByte;
    this.f = paramch;
  }

  // ERROR //
  public void a()
  {
    // Byte code:
    //   0: aconst_null
    //   1: astore_1
    //   2: invokestatic 49	java/lang/Thread:currentThread	()Ljava/lang/Thread;
    //   5: invokevirtual 53	java/lang/Thread:getId	()J
    //   8: invokestatic 59	java/lang/Long:valueOf	(J)Ljava/lang/Long;
    //   11: astore_2
    //   12: invokestatic 49	java/lang/Thread:currentThread	()Ljava/lang/Thread;
    //   15: new 61	java/lang/StringBuilder
    //   18: dup
    //   19: invokespecial 62	java/lang/StringBuilder:<init>	()V
    //   22: ldc 64
    //   24: invokevirtual 68	java/lang/StringBuilder:append	(Ljava/lang/String;)Ljava/lang/StringBuilder;
    //   27: aload_2
    //   28: invokevirtual 71	java/lang/StringBuilder:append	(Ljava/lang/Object;)Ljava/lang/StringBuilder;
    //   31: invokevirtual 74	java/lang/StringBuilder:toString	()Ljava/lang/String;
    //   34: invokevirtual 78	java/lang/Thread:setName	(Ljava/lang/String;)V
    //   37: new 80	org/apache/http/entity/ByteArrayEntity
    //   40: dup
    //   41: aload_0
    //   42: getfield 39	com/flurry/sdk/ce:e	[B
    //   45: invokespecial 83	org/apache/http/entity/ByteArrayEntity:<init>	([B)V
    //   48: astore_3
    //   49: aload_3
    //   50: ldc 85
    //   52: invokevirtual 88	org/apache/http/entity/ByteArrayEntity:setContentType	(Ljava/lang/String;)V
    //   55: new 90	org/apache/http/client/methods/HttpPost
    //   58: dup
    //   59: aload_0
    //   60: getfield 33	com/flurry/sdk/ce:b	Ljava/lang/String;
    //   63: invokespecial 92	org/apache/http/client/methods/HttpPost:<init>	(Ljava/lang/String;)V
    //   66: astore 11
    //   68: aload 11
    //   70: aload_3
    //   71: invokevirtual 96	org/apache/http/client/methods/HttpPost:setEntity	(Lorg/apache/http/HttpEntity;)V
    //   74: new 98	org/apache/http/params/BasicHttpParams
    //   77: dup
    //   78: invokespecial 99	org/apache/http/params/BasicHttpParams:<init>	()V
    //   81: astore 12
    //   83: aload 12
    //   85: sipush 10000
    //   88: invokestatic 105	org/apache/http/params/HttpConnectionParams:setConnectionTimeout	(Lorg/apache/http/params/HttpParams;I)V
    //   91: aload 12
    //   93: getstatic 27	com/flurry/sdk/ce:a	I
    //   96: invokestatic 108	org/apache/http/params/HttpConnectionParams:setSoTimeout	(Lorg/apache/http/params/HttpParams;I)V
    //   99: aload 11
    //   101: invokevirtual 112	org/apache/http/client/methods/HttpPost:getParams	()Lorg/apache/http/params/HttpParams;
    //   104: ldc 114
    //   106: iconst_0
    //   107: invokeinterface 120 3 0
    //   112: pop
    //   113: aload 12
    //   115: invokestatic 125	com/flurry/sdk/ew:b	(Lorg/apache/http/params/HttpParams;)Lorg/apache/http/client/HttpClient;
    //   118: astore 14
    //   120: aload 14
    //   122: astore 6
    //   124: aload 6
    //   126: aload 11
    //   128: invokeinterface 131 2 0
    //   133: astore 15
    //   135: aload 15
    //   137: astore 7
    //   139: aload 6
    //   141: ifnull +15 -> 156
    //   144: aload 6
    //   146: invokeinterface 135 1 0
    //   151: invokeinterface 140 1 0
    //   156: aload 7
    //   158: ifnull +13 -> 171
    //   161: aload 7
    //   163: invokeinterface 146 1 0
    //   168: ifnonnull +84 -> 252
    //   171: aload_0
    //   172: getfield 41	com/flurry/sdk/ce:f	Lcom/flurry/sdk/ch;
    //   175: aload_0
    //   176: getfield 35	com/flurry/sdk/ce:c	Ljava/lang/String;
    //   179: aload_0
    //   180: getfield 37	com/flurry/sdk/ce:d	Ljava/lang/String;
    //   183: invokeinterface 151 3 0
    //   188: return
    //   189: astore 5
    //   191: aconst_null
    //   192: astore 6
    //   194: bipush 6
    //   196: getstatic 25	com/flurry/sdk/ce:g	Ljava/lang/String;
    //   199: ldc 153
    //   201: aload 5
    //   203: invokestatic 158	com/flurry/sdk/ex:a	(ILjava/lang/String;Ljava/lang/String;Ljava/lang/Throwable;)V
    //   206: aconst_null
    //   207: astore 7
    //   209: aload 6
    //   211: ifnull -55 -> 156
    //   214: aload 6
    //   216: invokeinterface 135 1 0
    //   221: invokeinterface 140 1 0
    //   226: aconst_null
    //   227: astore 7
    //   229: goto -73 -> 156
    //   232: astore 4
    //   234: aload_1
    //   235: ifnull +14 -> 249
    //   238: aload_1
    //   239: invokeinterface 135 1 0
    //   244: invokeinterface 140 1 0
    //   249: aload 4
    //   251: athrow
    //   252: aload 7
    //   254: invokeinterface 146 1 0
    //   259: astore 8
    //   261: aload 8
    //   263: invokeinterface 164 1 0
    //   268: istore 9
    //   270: aload 8
    //   272: invokeinterface 167 1 0
    //   277: astore 10
    //   279: aload_0
    //   280: getfield 41	com/flurry/sdk/ce:f	Lcom/flurry/sdk/ch;
    //   283: iload 9
    //   285: aload 10
    //   287: aload_0
    //   288: getfield 35	com/flurry/sdk/ce:c	Ljava/lang/String;
    //   291: aload_0
    //   292: getfield 37	com/flurry/sdk/ce:d	Ljava/lang/String;
    //   295: invokeinterface 170 5 0
    //   300: return
    //   301: astore 4
    //   303: aload 6
    //   305: astore_1
    //   306: goto -72 -> 234
    //   309: astore 5
    //   311: goto -117 -> 194
    //
    // Exception table:
    //   from	to	target	type
    //   37	120	189	java/lang/Exception
    //   37	120	232	finally
    //   124	135	301	finally
    //   194	206	301	finally
    //   124	135	309	java/lang/Exception
  }
}

/* Location:           C:\Users\Admin\Desktop\Development Tools\ReEngineering\JavaApp\decompilers\classes_dex2jar.jar
 * Qualified Name:     com.flurry.sdk.ce
 * JD-Core Version:    0.6.0
 */