package com.flurry.sdk;

public class cj
{
  private static final String b = cj.class.getSimpleName();
  byte[] a;

  // ERROR //
  public cj(ck paramck)
    throws java.io.IOException
  {
    // Byte code:
    //   0: aload_0
    //   1: invokespecial 24	java/lang/Object:<init>	()V
    //   4: new 26	java/io/ByteArrayOutputStream
    //   7: dup
    //   8: invokespecial 27	java/io/ByteArrayOutputStream:<init>	()V
    //   11: astore_2
    //   12: new 29	java/io/DataOutputStream
    //   15: dup
    //   16: aload_2
    //   17: invokespecial 32	java/io/DataOutputStream:<init>	(Ljava/io/OutputStream;)V
    //   20: astore_3
    //   21: aload_3
    //   22: iconst_1
    //   23: invokevirtual 36	java/io/DataOutputStream:writeShort	(I)V
    //   26: aload_3
    //   27: aload_1
    //   28: invokevirtual 40	com/flurry/sdk/ck:a	()Ljava/lang/String;
    //   31: invokevirtual 44	java/io/DataOutputStream:writeUTF	(Ljava/lang/String;)V
    //   34: aload_3
    //   35: aload_1
    //   36: invokevirtual 47	com/flurry/sdk/ck:b	()J
    //   39: invokevirtual 51	java/io/DataOutputStream:writeLong	(J)V
    //   42: aload_3
    //   43: aload_1
    //   44: invokevirtual 54	com/flurry/sdk/ck:c	()J
    //   47: invokevirtual 51	java/io/DataOutputStream:writeLong	(J)V
    //   50: aload_3
    //   51: aload_1
    //   52: invokevirtual 57	com/flurry/sdk/ck:d	()J
    //   55: invokevirtual 51	java/io/DataOutputStream:writeLong	(J)V
    //   58: aload_3
    //   59: aload_1
    //   60: invokevirtual 60	com/flurry/sdk/ck:e	()Ljava/lang/String;
    //   63: invokevirtual 44	java/io/DataOutputStream:writeUTF	(Ljava/lang/String;)V
    //   66: aload_3
    //   67: aload_1
    //   68: invokevirtual 63	com/flurry/sdk/ck:f	()Ljava/lang/String;
    //   71: invokevirtual 44	java/io/DataOutputStream:writeUTF	(Ljava/lang/String;)V
    //   74: aload_3
    //   75: aload_1
    //   76: invokevirtual 67	com/flurry/sdk/ck:g	()I
    //   79: invokevirtual 70	java/io/DataOutputStream:writeByte	(I)V
    //   82: aload_3
    //   83: aload_1
    //   84: invokevirtual 73	com/flurry/sdk/ck:h	()Ljava/lang/String;
    //   87: invokevirtual 44	java/io/DataOutputStream:writeUTF	(Ljava/lang/String;)V
    //   90: aload_1
    //   91: invokevirtual 77	com/flurry/sdk/ck:i	()Landroid/location/Location;
    //   94: ifnonnull +207 -> 301
    //   97: aload_3
    //   98: iconst_0
    //   99: invokevirtual 81	java/io/DataOutputStream:writeBoolean	(Z)V
    //   102: aload_3
    //   103: aload_1
    //   104: invokevirtual 84	com/flurry/sdk/ck:j	()I
    //   107: invokevirtual 87	java/io/DataOutputStream:writeInt	(I)V
    //   110: aload_3
    //   111: iconst_m1
    //   112: invokevirtual 70	java/io/DataOutputStream:writeByte	(I)V
    //   115: aload_3
    //   116: iconst_m1
    //   117: invokevirtual 70	java/io/DataOutputStream:writeByte	(I)V
    //   120: aload_3
    //   121: aload_1
    //   122: invokevirtual 91	com/flurry/sdk/ck:k	()B
    //   125: invokevirtual 70	java/io/DataOutputStream:writeByte	(I)V
    //   128: aload_1
    //   129: invokevirtual 95	com/flurry/sdk/ck:l	()Ljava/lang/Long;
    //   132: ifnonnull +250 -> 382
    //   135: aload_3
    //   136: iconst_0
    //   137: invokevirtual 81	java/io/DataOutputStream:writeBoolean	(Z)V
    //   140: aload_1
    //   141: invokevirtual 99	com/flurry/sdk/ck:m	()Ljava/util/Map;
    //   144: astore 7
    //   146: aload 7
    //   148: ifnonnull +253 -> 401
    //   151: aload_3
    //   152: iconst_0
    //   153: invokevirtual 36	java/io/DataOutputStream:writeShort	(I)V
    //   156: aload_1
    //   157: invokevirtual 103	com/flurry/sdk/ck:n	()Ljava/util/List;
    //   160: astore 8
    //   162: aload 8
    //   164: ifnonnull +318 -> 482
    //   167: aload_3
    //   168: iconst_0
    //   169: invokevirtual 36	java/io/DataOutputStream:writeShort	(I)V
    //   172: aload_3
    //   173: aload_1
    //   174: invokevirtual 107	com/flurry/sdk/ck:o	()Z
    //   177: invokevirtual 81	java/io/DataOutputStream:writeBoolean	(Z)V
    //   180: aload_1
    //   181: invokevirtual 110	com/flurry/sdk/ck:q	()Ljava/util/List;
    //   184: astore 9
    //   186: aload 9
    //   188: ifnull +389 -> 577
    //   191: iconst_0
    //   192: istore 12
    //   194: iconst_0
    //   195: istore 13
    //   197: iconst_0
    //   198: istore 14
    //   200: iload 12
    //   202: aload 9
    //   204: invokeinterface 115 1 0
    //   209: if_icmpge +361 -> 570
    //   212: iload 13
    //   214: aload 9
    //   216: iload 12
    //   218: invokeinterface 119 2 0
    //   223: checkcast 121	com/flurry/sdk/ca
    //   226: invokevirtual 123	com/flurry/sdk/ca:a	()I
    //   229: iadd
    //   230: istore 13
    //   232: iload 13
    //   234: ldc 124
    //   236: if_icmple +352 -> 588
    //   239: iconst_5
    //   240: getstatic 18	com/flurry/sdk/cj:b	Ljava/lang/String;
    //   243: ldc 126
    //   245: invokestatic 131	com/flurry/sdk/ex:a	(ILjava/lang/String;Ljava/lang/String;)V
    //   248: iload 14
    //   250: istore 10
    //   252: aload_3
    //   253: aload_1
    //   254: invokevirtual 134	com/flurry/sdk/ck:p	()I
    //   257: invokevirtual 87	java/io/DataOutputStream:writeInt	(I)V
    //   260: aload_3
    //   261: iload 10
    //   263: invokevirtual 36	java/io/DataOutputStream:writeShort	(I)V
    //   266: iconst_0
    //   267: istore 11
    //   269: iload 11
    //   271: iload 10
    //   273: if_icmpge +259 -> 532
    //   276: aload_3
    //   277: aload 9
    //   279: iload 11
    //   281: invokeinterface 119 2 0
    //   286: checkcast 121	com/flurry/sdk/ca
    //   289: invokevirtual 137	com/flurry/sdk/ca:b	()[B
    //   292: invokevirtual 141	java/io/DataOutputStream:write	([B)V
    //   295: iinc 11 1
    //   298: goto -29 -> 269
    //   301: aload_3
    //   302: iconst_1
    //   303: invokevirtual 81	java/io/DataOutputStream:writeBoolean	(Z)V
    //   306: aload_3
    //   307: aload_0
    //   308: aload_1
    //   309: invokevirtual 77	com/flurry/sdk/ck:i	()Landroid/location/Location;
    //   312: invokevirtual 147	android/location/Location:getLatitude	()D
    //   315: invokevirtual 150	com/flurry/sdk/cj:a	(D)D
    //   318: invokevirtual 154	java/io/DataOutputStream:writeDouble	(D)V
    //   321: aload_3
    //   322: aload_0
    //   323: aload_1
    //   324: invokevirtual 77	com/flurry/sdk/ck:i	()Landroid/location/Location;
    //   327: invokevirtual 157	android/location/Location:getLongitude	()D
    //   330: invokevirtual 150	com/flurry/sdk/cj:a	(D)D
    //   333: invokevirtual 154	java/io/DataOutputStream:writeDouble	(D)V
    //   336: aload_3
    //   337: aload_1
    //   338: invokevirtual 77	com/flurry/sdk/ck:i	()Landroid/location/Location;
    //   341: invokevirtual 161	android/location/Location:getAccuracy	()F
    //   344: invokevirtual 165	java/io/DataOutputStream:writeFloat	(F)V
    //   347: goto -245 -> 102
    //   350: astore 5
    //   352: aload_3
    //   353: astore 6
    //   355: bipush 6
    //   357: getstatic 18	com/flurry/sdk/cj:b	Ljava/lang/String;
    //   360: ldc 167
    //   362: aload 5
    //   364: invokestatic 170	com/flurry/sdk/ex:a	(ILjava/lang/String;Ljava/lang/String;Ljava/lang/Throwable;)V
    //   367: aload 5
    //   369: athrow
    //   370: astore 4
    //   372: aload 6
    //   374: astore_3
    //   375: aload_3
    //   376: invokestatic 175	com/flurry/sdk/fh:a	(Ljava/io/Closeable;)V
    //   379: aload 4
    //   381: athrow
    //   382: aload_3
    //   383: iconst_1
    //   384: invokevirtual 81	java/io/DataOutputStream:writeBoolean	(Z)V
    //   387: aload_3
    //   388: aload_1
    //   389: invokevirtual 95	com/flurry/sdk/ck:l	()Ljava/lang/Long;
    //   392: invokevirtual 180	java/lang/Long:longValue	()J
    //   395: invokevirtual 51	java/io/DataOutputStream:writeLong	(J)V
    //   398: goto -258 -> 140
    //   401: aload_3
    //   402: aload 7
    //   404: invokeinterface 183 1 0
    //   409: invokevirtual 36	java/io/DataOutputStream:writeShort	(I)V
    //   412: aload 7
    //   414: invokeinterface 187 1 0
    //   419: invokeinterface 193 1 0
    //   424: astore 16
    //   426: aload 16
    //   428: invokeinterface 198 1 0
    //   433: ifeq -277 -> 156
    //   436: aload 16
    //   438: invokeinterface 202 1 0
    //   443: checkcast 204	java/util/Map$Entry
    //   446: astore 17
    //   448: aload_3
    //   449: aload 17
    //   451: invokeinterface 207 1 0
    //   456: checkcast 209	java/lang/String
    //   459: invokevirtual 44	java/io/DataOutputStream:writeUTF	(Ljava/lang/String;)V
    //   462: aload_3
    //   463: aload 17
    //   465: invokeinterface 212 1 0
    //   470: checkcast 214	com/flurry/sdk/bx$a
    //   473: getfield 217	com/flurry/sdk/bx$a:a	I
    //   476: invokevirtual 87	java/io/DataOutputStream:writeInt	(I)V
    //   479: goto -53 -> 426
    //   482: aload_3
    //   483: aload 8
    //   485: invokeinterface 115 1 0
    //   490: invokevirtual 36	java/io/DataOutputStream:writeShort	(I)V
    //   493: aload 8
    //   495: invokeinterface 218 1 0
    //   500: astore 15
    //   502: aload 15
    //   504: invokeinterface 198 1 0
    //   509: ifeq -337 -> 172
    //   512: aload_3
    //   513: aload 15
    //   515: invokeinterface 202 1 0
    //   520: checkcast 220	com/flurry/sdk/cb
    //   523: invokevirtual 222	com/flurry/sdk/cb:e	()[B
    //   526: invokevirtual 141	java/io/DataOutputStream:write	([B)V
    //   529: goto -27 -> 502
    //   532: aload_3
    //   533: iconst_0
    //   534: invokevirtual 36	java/io/DataOutputStream:writeShort	(I)V
    //   537: aload_3
    //   538: iconst_0
    //   539: invokevirtual 36	java/io/DataOutputStream:writeShort	(I)V
    //   542: aload_0
    //   543: aload_2
    //   544: invokevirtual 225	java/io/ByteArrayOutputStream:toByteArray	()[B
    //   547: putfield 227	com/flurry/sdk/cj:a	[B
    //   550: aload_3
    //   551: invokestatic 175	com/flurry/sdk/fh:a	(Ljava/io/Closeable;)V
    //   554: return
    //   555: astore 4
    //   557: aconst_null
    //   558: astore_3
    //   559: goto -184 -> 375
    //   562: astore 5
    //   564: aconst_null
    //   565: astore 6
    //   567: goto -212 -> 355
    //   570: iload 14
    //   572: istore 10
    //   574: goto -322 -> 252
    //   577: iconst_0
    //   578: istore 10
    //   580: goto -328 -> 252
    //   583: astore 4
    //   585: goto -210 -> 375
    //   588: iinc 14 1
    //   591: iinc 12 1
    //   594: goto -394 -> 200
    //
    // Exception table:
    //   from	to	target	type
    //   21	102	350	java/io/IOException
    //   102	140	350	java/io/IOException
    //   140	146	350	java/io/IOException
    //   151	156	350	java/io/IOException
    //   156	162	350	java/io/IOException
    //   167	172	350	java/io/IOException
    //   172	186	350	java/io/IOException
    //   200	232	350	java/io/IOException
    //   239	248	350	java/io/IOException
    //   252	266	350	java/io/IOException
    //   276	295	350	java/io/IOException
    //   301	347	350	java/io/IOException
    //   382	398	350	java/io/IOException
    //   401	426	350	java/io/IOException
    //   426	479	350	java/io/IOException
    //   482	502	350	java/io/IOException
    //   502	529	350	java/io/IOException
    //   532	550	350	java/io/IOException
    //   355	370	370	finally
    //   4	21	555	finally
    //   4	21	562	java/io/IOException
    //   21	102	583	finally
    //   102	140	583	finally
    //   140	146	583	finally
    //   151	156	583	finally
    //   156	162	583	finally
    //   167	172	583	finally
    //   172	186	583	finally
    //   200	232	583	finally
    //   239	248	583	finally
    //   252	266	583	finally
    //   276	295	583	finally
    //   301	347	583	finally
    //   382	398	583	finally
    //   401	426	583	finally
    //   426	479	583	finally
    //   482	502	583	finally
    //   502	529	583	finally
    //   532	550	583	finally
  }

  public cj(byte[] paramArrayOfByte)
  {
    this.a = paramArrayOfByte;
  }

  double a(double paramDouble)
  {
    return Math.round(paramDouble * 1000.0D) / 1000.0D;
  }

  public byte[] a()
  {
    return this.a;
  }
}

/* Location:           C:\Users\Admin\Desktop\Development Tools\ReEngineering\JavaApp\decompilers\classes_dex2jar.jar
 * Qualified Name:     com.flurry.sdk.cj
 * JD-Core Version:    0.6.0
 */